fn_cache/__init__.py
fn_cache/cli.py
fn_cache/config.py
fn_cache/decorators.py
fn_cache/enums.py
fn_cache/manager.py
fn_cache/storages.py
fn_cache/utils/__init__.py
fn_cache/utils/cache_key.py
fn_cache/utils/safe_oper.py
fn_cache/utils/serializers.py
fn_cache/utils/statistics.py
fn_cache-0.1.7.dist-info/licenses/LICENSE
fn_cache-0.1.7.dist-info/METADATA
fn_cache-0.1.7.dist-info/WHEEL
fn_cache-0.1.7.dist-info/entry_points.txt
fn_cache-0.1.7.dist-info/top_level.txt
fn_cache-0.1.7.dist-info/RECORD
