Metadata-Version: 2.4
Name: fn-cache
Version: 0.1.7
Summary: 轻量级通用缓存库
Home-page: https://github.com/leowzz/fn_cache
Author: LeoWang
Author-email: LeoWang <leolswq@163.com>
Maintainer-email: LeoWang <leolswq@163.com>
License: MIT
Project-URL: Homepage, https://github.com/leowzz/fn_cache
Project-URL: Documentation, https://fn-cache.readthedocs.io/
Project-URL: Repository, https://github.com/leowzz/fn_cache
Project-URL: Bug Tracker, https://github.com/leowzz/fn_cache/issues
Keywords: cache,memory,ttl,lru,async,decorator
Classifier: Development Status :: 5 - Production/Stable
Classifier: Intended Audience :: Developers
Classifier: Operating System :: OS Independent
Classifier: Programming Language :: Python :: 3
Classifier: Programming Language :: Python :: 3.8
Classifier: Programming Language :: Python :: 3.9
Classifier: Programming Language :: Python :: 3.10
Classifier: Programming Language :: Python :: 3.11
Classifier: Programming Language :: Python :: 3.12
Classifier: Topic :: Software Development :: Libraries :: Python Modules
Classifier: Topic :: System :: Distributed Computing
Classifier: Topic :: Database :: Database Engines/Servers
Requires-Python: >=3.8
License-File: LICENSE
Requires-Dist: typing-extensions>=4.0.0; python_version < "3.9"
Requires-Dist: pydantic<2.12,>2.10
Requires-Dist: fastapi<0.116.0,>0.100.0
Requires-Dist: loguru~=0.7.3
Provides-Extra: dev
Requires-Dist: pytest>=7.0.0; extra == "dev"
Requires-Dist: pytest-asyncio>=0.21.0; extra == "dev"
Requires-Dist: pytest-cov>=4.0.0; extra == "dev"
Requires-Dist: black>=23.0.0; extra == "dev"
Requires-Dist: isort>=5.12.0; extra == "dev"
Requires-Dist: flake8>=6.0.0; extra == "dev"
Requires-Dist: mypy>=1.0.0; extra == "dev"
Provides-Extra: docs
Requires-Dist: sphinx>=6.0.0; extra == "docs"
Requires-Dist: sphinx-rtd-theme>=1.2.0; extra == "docs"
Requires-Dist: myst-parser>=1.0.0; extra == "docs"
Dynamic: author
Dynamic: home-page
Dynamic: license-file
Dynamic: requires-python
